tiktok_trending/__init__.py
tiktok_trending/__main__.py
tiktok_trending-0.0.9.dist-info/METADATA
tiktok_trending-0.0.9.dist-info/WHEEL
tiktok_trending-0.0.9.dist-info/licenses/LICENSE
tiktok_trending-0.0.9.dist-info/RECORD
