Metadata-Version: 2.1
Name: tiktok_trending
Version: 0.0.9
Summary: Tiktok trending videos scraper
Project-URL: Homepage, https://github.com/ericlingit/tiktok-trending
Project-URL: Bug Tracker, https://github.com/ericlingit/tiktok-trending/issues
Author-email: Eric Lin <ericlingit@users.noreply.github.com>
License-File: LICENSE
Classifier: License :: OSI Approved :: GNU General Public License v3 (GPLv3)
Classifier: Operating System :: OS Independent
Classifier: Programming Language :: Python :: 3
Classifier: Topic :: Utilities
Requires-Python: >=3.7
Requires-Dist: brotli
Requires-Dist: requests
